mynyt/__init__.py
mynyt/config.py
mynyt/core.py
mynews-1.0.0.dist-info/METADATA
mynews-1.0.0.dist-info/WHEEL
mynews-1.0.0.dist-info/top_level.txt
mynews-1.0.0.dist-info/RECORD
