Metadata-Version: 2.2
Name: mynews
Version: 1.0.0
Summary: A library that accesses the publically availble RSS of NYT and converts it to an easy-to-digest daily summary.
Author-email: Kevin Zhu <kzhu2099@gmail.com>
Project-URL: Homepage, https://github.com/kzhu2099/MyNYT
Project-URL: Issues, https://github.com/kzhu2099/MyNYT/issues
Classifier: Programming Language :: Python :: 3
Classifier: Operating System :: OS Independent
Classifier: License :: OSI Approved :: MIT License
Requires-Python: >=3.8
Requires-Dist: feedparser
Requires-Dist: requests
Requires-Dist: pytz
